codex_cli/__init__.py
codex_cli/config.py
codex_cli/explain.py
codex_cli/main.py
codex_cli/script.py
codex_cli/visualize.py
codex_cli/core/__init__.py
codex_cli/core/openai_utils.py
codex_cli_studio-0.1.2.dist-info/licenses/LICENSE
codex_cli_studio-0.1.2.dist-info/METADATA
codex_cli_studio-0.1.2.dist-info/WHEEL
codex_cli_studio-0.1.2.dist-info/entry_points.txt
codex_cli_studio-0.1.2.dist-info/top_level.txt
codex_cli_studio-0.1.2.dist-info/RECORD
