Metadata-Version: 2.4
Name: codex-cli-studio
Version: 0.1.2
Summary: AI-powered CLI tools (explain, script, visualize, config) using OpenAI models.
Author: Michael Shapkin
License: Copyright 2025 Michael Shapkin
Project-URL: Homepage, https://github.com/michaelshapkin/codex-cli-studio
Project-URL: Repository, https://github.com/michaelshapkin/codex-cli-studio
Keywords: cli,ai,openai,codex,gpt,developer-tools,automation,visualization
Classifier: Development Status :: 3 - Alpha
Classifier: Intended Audience :: Developers
Classifier: Intended Audience :: System Administrators
Classifier: License :: OSI Approved :: MIT License
Classifier: Programming Language :: Python :: 3
Classifier: Programming Language :: Python :: 3.9
Classifier: Programming Language :: Python :: 3.10
Classifier: Programming Language :: Python :: 3.11
Classifier: Programming Language :: Python :: 3.12
Classifier: Programming Language :: Python :: 3.13
Classifier: Topic :: Software Development :: Libraries :: Python Modules
Classifier: Topic :: Utilities
Classifier: Environment :: Console
Classifier: Operating System :: OS Independent
Requires-Python: >=3.9
License-File: LICENSE
Requires-Dist: typer[all]<1.0.0,>=0.12.3
Requires-Dist: openai<2.0.0,>=1.30.1
Requires-Dist: python-dotenv<2.0.0,>=1.0.1
Requires-Dist: graphviz<1.0.0,>=0.20.1
Dynamic: license-file
